yahmc/__init__.py
yahmc-0.0.1.dist-info/METADATA
yahmc-0.0.1.dist-info/WHEEL
yahmc-0.0.1.dist-info/top_level.txt
yahmc-0.0.1.dist-info/RECORD
