Metadata-Version: 2.4
Name: yahmc
Version: 0.0.1
Summary: Empty
Project-URL: Homepage, https://pypi.org/project/yahmc/
Classifier: Programming Language :: Python :: 3
Classifier: License :: OSI Approved :: MIT License
Classifier: Operating System :: OS Independent
Requires-Python: >=3.8
